nazara/__init__.py
nazara/containers.py
nazara/ingestion/__init__.py
nazara/ingestion/application/__init__.py
nazara/ingestion/application/ingestion.py
nazara/ingestion/domain/__init__.py
nazara/ingestion/domain/models.py
nazara/ingestion/domain/contracts/__init__.py
nazara/ingestion/domain/contracts/ingestor_repository.py
nazara/ingestion/domain/contracts/signal_reader.py
nazara/ingestion/infrastructure/__init__.py
nazara/ingestion/infrastructure/containers.py
nazara/ingestion/infrastructure/django/__init__.py
nazara/ingestion/infrastructure/django/app/__init__.py
nazara/ingestion/infrastructure/django/app/admin.py
nazara/ingestion/infrastructure/django/app/apps.py
nazara/ingestion/infrastructure/django/app/models.py
nazara/ingestion/infrastructure/django/app/migrations/0001_initial.py
nazara/ingestion/infrastructure/django/app/migrations/__init__.py
nazara/ingestion/infrastructure/django/app/templates/admin/nazara_ingestion/ingestorconfig/change_form.html
nazara/ingestion/infrastructure/messaging/__init__.py
nazara/ingestion/infrastructure/messaging/tasks.py
nazara/ingestion/infrastructure/persistence/__init__.py
nazara/ingestion/infrastructure/persistence/repositories/__init__.py
nazara/ingestion/infrastructure/persistence/repositories/ingestor_config_repository.py
nazara/ingestion/infrastructure/readers/__init__.py
nazara/ingestion/infrastructure/readers/base.py
nazara/ingestion/infrastructure/readers/datadog_reader.py
nazara/ingestion/infrastructure/readers/incident_io_reader.py
nazara/ingestion/infrastructure/readers/intercom_reader.py
nazara/ingestion/infrastructure/readers/sentry_reader.py
nazara/intelligence/__init__.py
nazara/intelligence/application/__init__.py
nazara/intelligence/application/enrichment.py
nazara/intelligence/application/event_handlers.py
nazara/intelligence/application/flow_validator.py
nazara/intelligence/application/enrichers/__init__.py
nazara/intelligence/application/enrichers/base.py
nazara-0.1.0.dist-info/METADATA
nazara-0.1.0.dist-info/WHEEL
nazara-0.1.0.dist-info/RECORD
