Metadata-Version: 2.4
Name: nazara
Version: 0.1.0
Summary: Operational Knowledge Intelligence System - Turn operational signals into actionable intelligence
Project-URL: Homepage, https://gitlab.com/unified-proxy/microservices/nazara
Project-URL: Repository, https://gitlab.com/unified-proxy/microservices/nazara
Project-URL: Documentation, https://gitlab.com/unified-proxy/microservices/nazara/-/blob/main/README.md
Author-email: usantisteban <usantisteban@othercode.io>
License: MIT
Keywords: django,incidents,intelligence,monitoring,operations
Classifier: Development Status :: 3 - Alpha
Classifier: Environment :: Web Environment
Classifier: Framework :: Celery
Classifier: Framework :: Django
Classifier: Framework :: Django :: 4.2
Classifier: Framework :: Django :: 5.0
Classifier: Framework :: Django :: 5.1
Classifier: Intended Audience :: Developers
Classifier: License :: OSI Approved :: MIT License
Classifier: Operating System :: OS Independent
Classifier: Programming Language :: Python :: 3
Classifier: Programming Language :: Python :: 3.11
Classifier: Programming Language :: Python :: 3.12
Classifier: Topic :: System :: Monitoring
Requires-Python: >=3.11
Requires-Dist: anthropic>=0.75.0
Requires-Dist: celery>=5.3.0
Requires-Dist: datadog-api-client>=2.47.0
Requires-Dist: dependency-injector>=4.41.0
Requires-Dist: django-admin-inline-paginator-plus>=0.1.4
Requires-Dist: django-celery-beat>=2.5.0
Requires-Dist: django-celery-results>=2.5.0
Requires-Dist: django-json-widget>=2.1.1
Requires-Dist: django-select2>=8.4.7
Requires-Dist: django<6,>=4.2
Requires-Dist: openai>=2.12.0
Requires-Dist: pgvector>=0.2.0
Requires-Dist: psycopg2-binary>=2.9.0
Requires-Dist: python-incidentio-client>=0.56.4
Requires-Dist: redis>=4.5.0
Requires-Dist: requests>=2.32.5
Provides-Extra: all-integrations
Requires-Dist: datadog-api-client>=2.0.0; extra == 'all-integrations'
Requires-Dist: python-incidentio-client>=0.50.0; extra == 'all-integrations'
Provides-Extra: datadog
Requires-Dist: datadog-api-client>=2.0.0; extra == 'datadog'
Provides-Extra: dev
Requires-Dist: celery-types>=0.22.0; extra == 'dev'
Requires-Dist: django-stubs>=4.2.0; extra == 'dev'
Requires-Dist: mypy>=1.10.0; extra == 'dev'
Requires-Dist: pytest-cov>=5.0.0; extra == 'dev'
Requires-Dist: pytest-django>=4.8.0; extra == 'dev'
Requires-Dist: pytest>=8.0.0; extra == 'dev'
Requires-Dist: ruff>=0.4.0; extra == 'dev'
Provides-Extra: incident-io
Requires-Dist: python-incidentio-client>=0.50.0; extra == 'incident-io'
